db_first/__init__.py
db_first/base_model.py
db_first/exc.py
db_first/statement_maker.py
db_first/actions/__init__.py
db_first/actions/base.py
db_first/actions/web.py
db_first/dbal/__init__.py
db_first/dbal/exceptions.py
db_first/dbal/paginate.py
db_first/dbal/sqla.py
db_first/schemas/__init__.py
db_first/schemas/base.py
db_first/schemas/paginate.py
db_first-5.0.0.dist-info/licenses/LICENSE
db_first-5.0.0.dist-info/METADATA
db_first-5.0.0.dist-info/WHEEL
db_first-5.0.0.dist-info/top_level.txt
db_first-5.0.0.dist-info/RECORD
