Metadata-Version: 2.4
Name: DB-First
Version: 5.0.0
Summary: CRUD tools for working with database via SQLAlchemy.
Author-email: Konstantin Fadeev <fadeev@legalact.pro>
License: MIT License
Project-URL: changelog, https://github.com/flask-pro/db-first/blob/master/CHANGES.md
Project-URL: repository, https://github.com/flask-pro/db-first
Classifier: Development Status :: 5 - Production/Stable
Classifier: Intended Audience :: Developers
Classifier: License :: OSI Approved :: MIT License
Classifier: Operating System :: OS Independent
Classifier: Programming Language :: Python :: 3 :: Only
Classifier: Programming Language :: Python :: Implementation :: CPython
Classifier: Topic :: Database
Classifier: Topic :: Software Development :: Libraries
Requires-Python: >=3.11
License-File: LICENSE
Requires-Dist: SQLAlchemy>=2.0.0
Requires-Dist: marshmallow>=3.14.1
Provides-Extra: dev
Requires-Dist: build==1.3.0; extra == "dev"
Requires-Dist: psycopg[binary]==3.3.2; extra == "dev"
Requires-Dist: pre-commit==4.5.0; extra == "dev"
Requires-Dist: pytest==9.0.2; extra == "dev"
Requires-Dist: pytest-cov==7.0.0; extra == "dev"
Requires-Dist: python-dotenv==1.2.1; extra == "dev"
Requires-Dist: tox==4.30.3; extra == "dev"
Requires-Dist: twine==6.2.0; extra == "dev"
Dynamic: license-file
